{
  "60ad1c2b0e1d633fc7ef2e69_Group 160-min-p-500.jpeg": {
    "mime": "image/jpeg"
  },
  "Screenshot_2.png": {
    "mime": "image/png"
  },
  "5fef584362e74acfa6b75398_Group 51.svg": {
    "mime": "image/svg+xml"
  },
  "8.svg": {
    "mime": "image/svg+xml"
  },
  "5fef5843b6409375f7c23f2b_Group 17.svg": {
    "mime": "image/svg+xml"
  },
  "5fef58435ceaed068dde60ca_Group 16.svg": {
    "mime": "image/svg+xml"
  },
  "6077dc9bcd0f7a437038f60d_image_processing20200129-19798-1k8ponz 1-min-p-500.png": {
    "mime": "image/png"
  },
  "6077dcd635f7f176db9fef1e_image_processing20200129-19798-1k8ponz 3-min-p-500.png": {
    "mime": "image/png"
  },
  "6077dce7ec07854a8c820c4e_image_processing20200129-19798-1k8ponz 4-min-p-500.png": {
    "mime": "image/png"
  },
  "4.png": {
    "mime": "image/png"
  },
  "3.png": {
    "mime": "image/png"
  },
  "5.png": {
    "mime": "image/png"
  },
  "1.png": {
    "mime": "image/png"
  },
  "10.jpg": {
    "mime": "image/jpeg"
  },
  "11.jfif": {
    "mime": "image/jpeg"
  },
  "7.svg": {
    "mime": "image/svg+xml"
  },
  "9.svg": {
    "mime": "image/svg+xml"
  },
  "12.png": {
    "mime": "image/png"
  },
  "Screenshot_3.png": {
    "mime": "image/png"
  },
  "Screenshot_4.png": {
    "mime": "image/png"
  }
}